{
  "edu.westga.cs3212.inventory_manager.model.Product@c3b98eb8": 34,
  "edu.westga.cs3212.inventory_manager.model.Product@5c07cd45": 22,
  "edu.westga.cs3212.inventory_manager.model.Product@2018c35a": 49,
  "edu.westga.cs3212.inventory_manager.model.Product@6613f651": 40,
  "edu.westga.cs3212.inventory_manager.model.Product@7efb9cfc": 42,
  "edu.westga.cs3212.inventory_manager.model.Product@70e18b6e": 2,
  "edu.westga.cs3212.inventory_manager.model.Product@808f079f": 3,
  "edu.westga.cs3212.inventory_manager.model.Product@f4c07112": 48,
  "edu.westga.cs3212.inventory_manager.model.Product@272fedfc": 27,
  "edu.westga.cs3212.inventory_manager.model.Product@6a5d81cb": 36,
  "edu.westga.cs3212.inventory_manager.model.Product@1b28487f": 18,
  "edu.westga.cs3212.inventory_manager.model.Product@e9be8ba9": 14,
  "edu.westga.cs3212.inventory_manager.model.Product@7bc4869f": 25,
  "edu.westga.cs3212.inventory_manager.model.Product@576b4337": 50,
  "edu.westga.cs3212.inventory_manager.model.Product@7b478161": 9,
  "edu.westga.cs3212.inventory_manager.model.Product@8ab42992": 21,
  "edu.westga.cs3212.inventory_manager.model.Product@84f36b14": 10,
  "edu.westga.cs3212.inventory_manager.model.Product@79bf77d8": 32,
  "edu.westga.cs3212.inventory_manager.model.Product@4d104d7c": 10,
  "edu.westga.cs3212.inventory_manager.model.Product@b631271f": 21,
  "edu.westga.cs3212.inventory_manager.model.Product@bbbff2d0": 25,
  "edu.westga.cs3212.inventory_manager.model.Product@c8ebe71a": 22,
  "edu.westga.cs3212.inventory_manager.model.Product@fba8089e": 42,
  "edu.westga.cs3212.inventory_manager.model.Product@bcda95e6": 23,
  "edu.westga.cs3212.inventory_manager.model.Product@f2a61e5b": 28
}